src/piso/piso_12bit.v
module piso_12bit (
    input  wire        clk,        // Master clock cepat (misal 12.288 MHz)
    input  wire        rst_n,      // Reset aktif-rendah (asinkron)
    input  wire        load_en,    // Sinyal strobe dari clock_div / CIC (48 kHz)
    input  wire [11:0] data_in,    // Output 12-bit dari filter CIC
    output wire        serial_out  // 1 Pin output data serial
);

    reg [11:0] shift_reg;

    always @(posedge clk or negedge rst_n) begin
        if (!rst_n) begin
            shift_reg <= 12'b0;
        end else begin
            if (load_en) begin
                // Muat 12-bit paralel saat data baru dari CIC siap
                shift_reg <= data_in;
            end else begin
                // Geser 1 bit ke kiri setiap siklus clock
                shift_reg <= {shift_reg[10:0], 1'b0};
            end
        end
    end

    // MSB dikirim terlebih dahulu ke pin serial luar
    assign serial_out = shift_reg[11];

endmodule

src/piso/tb_piso_12bit.v
`timescale 1ns / 1ps

module tb_piso_12bit;

    // 1. Deklarasi Sinyal Stimulus Testbench
    reg         clk;
    reg         rst_n;
    reg         load_en;
    reg  [11:0] data_in;
    wire        serial_out;

    // 2. Instansiasi Unit Under Test (UUT)
    piso_12bit uut (
        .clk        (clk),
        .rst_n      (rst_n),
        .load_en    (load_en),
        .data_in    (data_in),
        .serial_out (serial_out)
    );

    // 3. Pembangkit Master Clock (12.288 MHz -> Periode = 81.38 ns, Half-period = 40.69 ns)
    always begin
        #40.69 clk = ~clk;
    end

    // 4. Skenario Pengujian (Stimulus)
    initial begin
        // Perekaman gelombang VCD untuk GTKWave
        $dumpfile("piso_12bit_sim.vcd");
        $dumpvars(0, tb_piso_12bit);

        // Kondisi Awal (Detik ke-0)
        clk     = 1'b0;
        rst_n   = 1'b0; // Reset aktif
        load_en = 1'b0;
        data_in = 12'd0;

        // Lepaskan reset setelah beberapa siklus
        #200;
        rst_n = 1'b1;
        #80;

        // --- SKENARIO 1: Muat Data Pertama (Contoh: 12'b1010_1100_0101 = 0xAC5) ---
        @(negedge clk);
        data_in = 12'b1010_1100_0101;
        load_en = 1'b1; // Aktifkan sinyal Load
        @(negedge clk);
        load_en = 1'b0; // Matikan Load agar PISO mulai menggeser data

        // Tunggu selama 12 siklus clock penuh untuk melihat seluruh 12-bit tergeser keluar
        repeat (12) @(posedge clk);

        // Jeda waktu antar paket sampel
        #200;

        // --- SKENARIO 2: Muat Data Kedua (Skala Penuh ADC: 12'd2048 = 12'b1000_0000_0000) ---
        @(negedge clk);
        data_in = 12'd2048;
        load_en = 1'b1;
        @(negedge clk);
        load_en = 1'b0;

        // Tunggu pergeseran 12-bit selesai
        repeat (12) @(posedge clk);

        #300;
        $display("[INFO] Simulasi PISO 12-bit selesai dengan sukses.");
        $finish;
    end

endmodule

src/piso/piso_12bit_sim.vcd
$date
	Tue Aug 25 21:38:39 2026
$end
$version
	Icarus Verilog
$end
$timescale
	1ps
$end
$scope module tb_piso_12bit $end
$var wire 1 ! serial_out $end
$var reg 1 " clk $end
$var reg 12 # data_in [11:0] $end
$var reg 1 $ load_en $end
$var reg 1 % rst_n $end
$scope module uut $end
$var wire 1 " clk $end
$var wire 12 & data_in [11:0] $end
$var wire 1 $ load_en $end
$var wire 1 % rst_n $end
$var wire 1 ! serial_out $end
$var reg 12 ' shift_reg [11:0] $end
$upscope $end
$upscope $end
$enddefinitions $end
$comment Show the parameter values. $end
$dumpall
$end
#0
$dumpvars
b0 '
b0 &
0%
0$
b0 #
0"
0!
$end
#40690
1"
#81380
0"
#122070
1"
#162760
0"
#200000
1%
#203450
1"
#244140
0"
#284830
1"
#325520
1$
b101011000101 #
b101011000101 &
0"
#366210
1!
b101011000101 '
1"
#406900
0$
0"
#447590
0!
b10110001010 '
1"
#488280
0"
#528970
1!
b101100010100 '
1"
#569660
0"
#610350
0!
b11000101000 '
1"
#651040
0"
#691730
1!
b110001010000 '
1"
#732420
0"
#773110
b100010100000 '
1"
#813800
0"
#854490
0!
b101000000 '
1"
#895180
0"
#935870
b1010000000 '
1"
#976560
0"
#1017250
b10100000000 '
1"
#1057940
0"
#1098630
1!
b101000000000 '
1"
#1139320
0"
#1180010
0!
b10000000000 '
1"
#1220700
0"
#1261390
1!
b100000000000 '
1"
#1302080
0"
#1342770
0!
b0 '
1"
#1383460
0"
#1424150
1"
#1464840
0"
#1505530
1"
#1546220
1$
b100000000000 #
b100000000000 &
0"
#1586910
1!
b100000000000 '
1"
#1627600
0$
0"
#1668290
0!
b0 '
1"
